acct_mgr/__init__.py
acct_mgr/admin.py
acct_mgr/api.py
acct_mgr/compat.py
acct_mgr/db.py
acct_mgr/guard.py
acct_mgr/htfile.py
acct_mgr/htfile.pyi
acct_mgr/http.py
acct_mgr/macros.py
acct_mgr/model.py
acct_mgr/notification.py
acct_mgr/pwhash.py
acct_mgr/pwhash.pyi
acct_mgr/register.py
acct_mgr/svnserve.py
acct_mgr/util.py
acct_mgr/web_ui.py
acct_mgr/htdocs/acctmgr.css
acct_mgr/htdocs/approval.png
acct_mgr/htdocs/arrow.png
acct_mgr/htdocs/delete.png
acct_mgr/htdocs/guard.png
acct_mgr/htdocs/info.png
acct_mgr/htdocs/locked.png
acct_mgr/htdocs/refresh.png
acct_mgr/htdocs/status_disabled.png
acct_mgr/htdocs/status_error.png
acct_mgr/htdocs/status_ok.png
acct_mgr/htdocs/status_unknown.png
acct_mgr/htdocs/time-locked.png
acct_mgr/htdocs/users.png
acct_mgr/htdocs/js/acctmgr_admin.js
acct_mgr/locale/.placeholder
acct_mgr/locale/cs/LC_MESSAGES/acct_mgr.mo
acct_mgr/locale/de/LC_MESSAGES/acct_mgr.mo
acct_mgr/locale/es/LC_MESSAGES/acct_mgr.mo
acct_mgr/locale/et/LC_MESSAGES/acct_mgr.mo
acct_mgr/locale/fi/LC_MESSAGES/acct_mgr.mo
acct_mgr/locale/fr/LC_MESSAGES/acct_mgr.mo
acct_mgr/locale/he/LC_MESSAGES/acct_mgr.mo
acct_mgr/locale/id_ID/LC_MESSAGES/acct_mgr.mo
acct_mgr/locale/it/LC_MESSAGES/acct_mgr.mo
acct_mgr/locale/ja/LC_MESSAGES/acct_mgr.mo
acct_mgr/locale/nl/LC_MESSAGES/acct_mgr.mo
acct_mgr/locale/pl/LC_MESSAGES/acct_mgr.mo
acct_mgr/locale/pt_BR/LC_MESSAGES/acct_mgr.mo
acct_mgr/locale/ru/LC_MESSAGES/acct_mgr.mo
acct_mgr/locale/sv/LC_MESSAGES/acct_mgr.mo
acct_mgr/locale/te/LC_MESSAGES/acct_mgr.mo
acct_mgr/locale/tr/LC_MESSAGES/acct_mgr.mo
acct_mgr/locale/uk/LC_MESSAGES/acct_mgr.mo
acct_mgr/locale/zh_CN/LC_MESSAGES/acct_mgr.mo
acct_mgr/locale/zh_TW/LC_MESSAGES/acct_mgr.mo
acct_mgr/opt/__init__.py
acct_mgr/opt/radius.py
acct_mgr/opt/announcer/__init__.py
acct_mgr/opt/announcer/uid_chg.py
acct_mgr/opt/tracforms/__init__.py
acct_mgr/opt/tracforms/uid_chg.py
acct_mgr/opt/tracscreenshots/__init__.py
acct_mgr/opt/tracscreenshots/uid_chg.py
acct_mgr/opt/tracvote/__init__.py
TracAccountManager-0.6.0.dist-info/COPYING
TracAccountManager-0.6.0.dist-info/METADATA
TracAccountManager-0.6.0.dist-info/WHEEL
TracAccountManager-0.6.0.dist-info/entry_points.txt
TracAccountManager-0.6.0.dist-info/top_level.txt
TracAccountManager-0.6.0.dist-info/zip-safe
TracAccountManager-0.6.0.dist-info/RECORD
